vidya/__init__.py
vidya/__main__.py
vidya/main.py
vidya/transform.py
vidya/utils/__init__.py
vidya/utils/css_to_csv.py
vidya/utils/os.py
vidya-0.1.1.dist-info/METADATA
vidya-0.1.1.dist-info/WHEEL
vidya-0.1.1.dist-info/entry_points.txt
vidya-0.1.1.dist-info/RECORD
