Metadata-Version: 2.1
Name: vidya
Version: 0.1.1
Summary: My personal assitant capable of doing many things.
Author: suusojeat
Author-email: suusojeat@gmail.com
Requires-Python: >=3.11,<4.0
Classifier: Programming Language :: Python :: 3
Classifier: Programming Language :: Python :: 3.11
Requires-Dist: cssutils (>=2.6.0,<3.0.0)
Requires-Dist: typer[all] (>=0.7.0,<0.8.0)
